trexio.py
pytrexio/_version.py
pytrexio/pytrexio.py
pytrexio/__init__.py
pytrexio/_pytrexio.cpython-38-darwin.so
pytrexio/.dylibs/libhdf5.200.dylib
trexio-2.6.0.dist-info/RECORD
trexio-2.6.0.dist-info/LICENSE
trexio-2.6.0.dist-info/AUTHORS
trexio-2.6.0.dist-info/WHEEL
trexio-2.6.0.dist-info/COPYING
trexio-2.6.0.dist-info/top_level.txt
trexio-2.6.0.dist-info/METADATA
