Metadata-Version: 2.1
Name: trexio
Version: 2.6.0
Summary: Python API of the TREXIO library
Home-page: https://github.com/TREX-CoE/trexio
Author: TREX-CoE
Author-email: posenitskiy@irsamc.ups-tlse.fr
License: BSD-3-Clause
Project-URL: Bug Tracker, https://github.com/TREX-CoE/trexio/issues
Classifier: Intended Audience :: Science/Research
Classifier: Intended Audience :: Developers
Classifier: Topic :: Scientific/Engineering
Classifier: Programming Language :: C
Classifier: Programming Language :: Python
Classifier: Programming Language :: Python :: 3
Classifier: Programming Language :: Python :: 3 :: Only
Classifier: Programming Language :: Python :: Implementation :: CPython
Classifier: Operating System :: POSIX
Classifier: Operating System :: Unix
Classifier: Operating System :: MacOS
Requires-Python: >=3.6
License-File: LICENSE
License-File: COPYING
License-File: AUTHORS
Requires-Dist: numpy>=1.17.3
